Metadata-Version: 2.1
Name: kaneki
Version: 0.1.0
Summary: MODULE FOR REAL GHOULS AND DEADINSIDES!!! 1000 - 7???
Home-page: https://github.com/gl0ckchan/kaneki
Author: gl0ckchan
Author-email: dragonelite110@gmail.com
License: UNKNOWN
Platform: UNKNOWN
